redlite/__init__.py
redlite/__main__.py
redlite/_core.py
redlite/_dummy_storage.py
redlite/_jsonl_storage.py
redlite/_lock.py
redlite/_run.py
redlite/_stats.py
redlite/_util.py
redlite/benchmark/aime24.py
redlite/benchmark/aime25.py
redlite/benchmark/gpqa.py
redlite/benchmark/livecodebench.py
redlite/benchmark/math500.py
redlite/benchmark/mmlu_pro.py
redlite/dataset/__init__.py
redlite/dataset/_hf.py
redlite/dataset/_inno.py
redlite/dataset/_load.py
redlite/dataset/_strip_system.py
redlite/dataset/json_dataset.py
redlite/dataset/memory_dataset.py
redlite/metric/__init__.py
redlite/metric/_basic.py
redlite/metric/_best_of.py
redlite/metric/_random.py
redlite/metric/_rejection.py
redlite/metric/util.py
redlite/metric/bleu/__init__.py
redlite/metric/f1/__init__.py
redlite/metric/math/__init__.py
redlite/metric/math/_parser.py
redlite/metric/math/_score.py
redlite/metric/rouge/__init__.py
redlite/model/__init__.py
redlite/model/_dummy.py
redlite/model/_ignore_system.py
redlite/model/_moderation.py
redlite/model/_remove_thinking.py
redlite/model/_throttle.py
redlite/model/anthropic_model.py
redlite/model/aws_bedrock_model.py
redlite/model/gemini_model.py
redlite/model/hf_model.py
redlite/model/llamacpp_model.py
redlite/model/openai_model.py
redlite/server/__init__.py
redlite/server/_app.py
redlite/server/resources/default/3rdpartylicenses.txt
redlite/server/resources/default/color.dae87a04d07ca92b.png
redlite/server/resources/default/favicon.ico
redlite/server/resources/default/fontawesome-webfont.2b13baa7dd4f54c9.eot
redlite/server/resources/default/fontawesome-webfont.8a7cb27d142e3e19.ttf
redlite/server/resources/default/fontawesome-webfont.cf011583fb81df9f.woff
redlite/server/resources/default/fontawesome-webfont.da909aa098b0ee2d.svg
redlite/server/resources/default/fontawesome-webfont.e9955780856cf8aa.woff2
redlite/server/resources/default/hue.8b1818380241e6ac.png
redlite/server/resources/default/index.html
redlite/server/resources/default/main.0a4aec223293494a.js
redlite-0.4.3.dist-info/licenses/LICENSE
redlite-0.4.3.dist-info/METADATA
redlite-0.4.3.dist-info/WHEEL
redlite-0.4.3.dist-info/entry_points.txt
redlite-0.4.3.dist-info/top_level.txt
redlite-0.4.3.dist-info/RECORD
