Metadata-Version: 2.4
Name: redlite
Version: 0.4.3
Summary: LLM testing on steroids
Author-email: Mike Kroutikov <mkroutikov@innodata.com>, David Nadeau <dnadeau@innodata.com>
License: MIT License
Project-URL: Homepage, https://github.com/innodatalabs/redlite
Project-URL: Documentation, https://innodatalabs.github.io/redlite
Project-URL: Repository, https://github.com/innodatalabs/redlite.git
Project-URL: Issues, https://github.com/innodatalabs/redlite/issues
Keywords: large langualge models,evaluation,datasets
Classifier: Development Status :: 4 - Beta
Classifier: Intended Audience :: Developers
Classifier: License :: OSI Approved :: MIT License
Classifier: Programming Language :: Python :: 3
Classifier: Programming Language :: Python :: 3.10
Classifier: Programming Language :: Python :: 3.11
Classifier: Programming Language :: Python :: 3.12
Requires-Python: >=3.10
License-File: LICENSE
Requires-Dist: duoname~=0.0.2
Requires-Dist: tqdm
Provides-Extra: hf
Requires-Dist: datasets; extra == "hf"
Provides-Extra: server
Requires-Dist: aiohttp~=3.9.0; extra == "server"
Requires-Dist: aiohttp-cors; extra == "server"
Provides-Extra: openai
Requires-Dist: openai; extra == "openai"
Provides-Extra: anthropic
Requires-Dist: anthropic~=0.64.0; extra == "anthropic"
Provides-Extra: zeno
Requires-Dist: zeno_client; extra == "zeno"
Provides-Extra: rouge
Requires-Dist: rouge-score; extra == "rouge"
Provides-Extra: bleu
Requires-Dist: nltk; extra == "bleu"
Provides-Extra: aws
Requires-Dist: boto3; extra == "aws"
Provides-Extra: llama-cpp
Requires-Dist: llama-cpp-python; extra == "llama-cpp"
Provides-Extra: google
Requires-Dist: google-genai; extra == "google"
Provides-Extra: math
Requires-Dist: pyparsing; extra == "math"
Provides-Extra: all
Requires-Dist: redlite[anthropic,aws,bleu,google,hf,llama-cpp,math,openai,rouge,server,zeno]; extra == "all"
Provides-Extra: dev
Requires-Dist: pytest; extra == "dev"
Requires-Dist: twine; extra == "dev"
Requires-Dist: portray; extra == "dev"
Requires-Dist: black; extra == "dev"
Requires-Dist: flake8; extra == "dev"
Requires-Dist: mypy; extra == "dev"
Requires-Dist: pytest-asyncio==0.24.0; extra == "dev"
Requires-Dist: pytest-aiohttp; extra == "dev"
Dynamic: license-file
